stability_sdk/__init__.py
stability_sdk/__main__.py
stability_sdk/animation.py
stability_sdk/animation_ui.py
stability_sdk/api.py
stability_sdk/client.py
stability_sdk/matrix.py
stability_sdk/utils.py
stability_sdk/interfaces/__init__.py
stability_sdk/interfaces/gooseai/__init__.py
stability_sdk/interfaces/gooseai/dashboard/dashboard_pb2.py
stability_sdk/interfaces/gooseai/dashboard/dashboard_pb2_grpc.py
stability_sdk/interfaces/gooseai/engines/engines_pb2.py
stability_sdk/interfaces/gooseai/engines/engines_pb2_grpc.py
stability_sdk/interfaces/gooseai/finetuning/finetuning_pb2.py
stability_sdk/interfaces/gooseai/finetuning/finetuning_pb2_grpc.py
stability_sdk/interfaces/gooseai/generation/__init__.py
stability_sdk/interfaces/gooseai/generation/generation_pb2.py
stability_sdk/interfaces/gooseai/generation/generation_pb2_grpc.py
stability_sdk/interfaces/gooseai/generation/tensors_pb2.py
stability_sdk/interfaces/gooseai/project/project_pb2.py
stability_sdk/interfaces/gooseai/project/project_pb2_grpc.py
stability_sdk/interfaces/src/tensorizer/ATTIC/test_protobuf.py
stability_sdk/interfaces/src/tensorizer/ATTIC/test_tensorizer.py
stability_sdk/interfaces/src/tensorizer/examples/__init__.py
stability_sdk/interfaces/src/tensorizer/examples/deserialize.py
stability_sdk/interfaces/src/tensorizer/examples/hf_serialization.py
stability_sdk/interfaces/src/tensorizer/examples/serialize.py
stability_sdk/interfaces/src/tensorizer/tensorizer/__init__.py
stability_sdk/interfaces/src/tensorizer/tensorizer/_wide_pipes.py
stability_sdk/interfaces/src/tensorizer/tensorizer/protobuf.py
stability_sdk/interfaces/src/tensorizer/tensorizer/serialization.py
stability_sdk/interfaces/src/tensorizer/tensorizer/stream_io.py
stability_sdk/interfaces/src/tensorizer/tensorizer/tensors_pb2.py
stability_sdk/interfaces/src/tensorizer/tensorizer/utils.py
stability_sdk/interfaces/src/tensorizer/tensors/__init__.py
stability_sdk/interfaces/src/tensorizer/tensors/tensors_pb2.py
stability_sdk-0.8.5.dist-info/LICENSE
stability_sdk-0.8.5.dist-info/METADATA
stability_sdk-0.8.5.dist-info/WHEEL
stability_sdk-0.8.5.dist-info/top_level.txt
stability_sdk-0.8.5.dist-info/RECORD
