Metadata-Version: 2.1
Name: stability-sdk
Version: 0.8.5
Summary: Python SDK for interacting with stability.ai APIs
Home-page: https://beta.dreamstudio.ai/
Download-URL: https://github.com/Stability-AI/stability-sdk/
Author: Stability AI
Author-email: support@stability.ai
Maintainer: Stability AI
Maintainer-email: support@stability.ai
License: MIT
Classifier: Intended Audience :: Developers
Classifier: Intended Audience :: Education
Classifier: Intended Audience :: End Users/Desktop
Classifier: Intended Audience :: Science/Research
Classifier: Topic :: Artistic Software
Classifier: Topic :: Education
Classifier: Topic :: Games/Entertainment
Classifier: Topic :: Internet :: WWW/HTTP :: Dynamic Content
Classifier: Topic :: Internet :: WWW/HTTP :: Dynamic Content :: CGI Tools/Libraries
Classifier: Topic :: Multimedia
Classifier: Topic :: Multimedia :: Graphics
Classifier: Topic :: Multimedia :: Graphics :: 3D Rendering
Classifier: Topic :: Multimedia :: Graphics :: Editors
Classifier: Topic :: Multimedia :: Graphics :: Editors :: Raster-Based
Classifier: Topic :: Scientific/Engineering
Classifier: Topic :: Scientific/Engineering :: Artificial Intelligence
Classifier: Topic :: Scientific/Engineering :: Human Machine Interfaces
Classifier: Topic :: Scientific/Engineering :: Image Processing
License-File: LICENSE
Requires-Dist: Pillow
Requires-Dist: grpcio==1.53.0
Requires-Dist: grpcio-tools==1.53.0
Requires-Dist: python-dotenv
Requires-Dist: param
Requires-Dist: protobuf==4.21.12
Provides-Extra: dev
Requires-Dist: pytest; extra == "dev"
Requires-Dist: grpcio-testing; extra == "dev"
Provides-Extra: anim
Requires-Dist: keyframed; extra == "anim"
Requires-Dist: numpy; extra == "anim"
Requires-Dist: opencv-python-headless; extra == "anim"
Provides-Extra: anim-ui
Requires-Dist: keyframed; extra == "anim-ui"
Requires-Dist: gradio==3.50.2; extra == "anim-ui"
Requires-Dist: numpy; extra == "anim-ui"
Requires-Dist: opencv-python-headless; extra == "anim-ui"
Requires-Dist: tqdm; extra == "anim-ui"
